drf_utils/__init__.py
drf_utils/metadata.py
drf_utils/serializers/models.py
drf_utils/serializers/__init__.py
djangorestframework_utils-0.0.1.dist-info/WHEEL
djangorestframework_utils-0.0.1.dist-info/metadata.json
djangorestframework_utils-0.0.1.dist-info/RECORD
djangorestframework_utils-0.0.1.dist-info/DESCRIPTION.rst
djangorestframework_utils-0.0.1.dist-info/METADATA
djangorestframework_utils-0.0.1.dist-info/top_level.txt
