Metadata-Version: 2.0
Name: djangorestframework-utils
Version: 0.0.1
Summary: Utilities for Django REST Framework
Home-page: https://github.com/benzid-wael/django-rest-framework-utils
Author: Wael BEN ZID
Author-email: benzid.wael@hotmail.fr
License: BSD
Platform: UNKNOWN
Classifier: Development Status :: 2 - Pre-Alpha
Classifier: Environment :: Web Environment
Classifier: Framework :: Django
Classifier: Intended Audience :: Developers
Classifier: License :: OSI Approved :: BSD License
Classifier: Operating System :: OS Independent
Classifier: Natural Language :: English
Classifier: Programming Language :: Python :: 2
Classifier: Programming Language :: Python :: 2.7
Classifier: Programming Language :: Python :: 3
Classifier: Programming Language :: Python :: 3.3
Classifier: Programming Language :: Python :: 3.4
Classifier: Topic :: Internet :: WWW/HTTP
